{
  "main": {
    "id": "fe36c3a68711eb60",
    "type": "split",
    "children": [
      {
        "id": "6506616b1c256d0c",
        "type": "tabs",
        "children": [
          {
            "id": "b9810ce725926b7d",
            "type": "leaf",
            "state": {
              "type": "markdown",
              "state": {
                "file": "Welcome.md",
                "mode": "source",
                "source": false
              }
            }
          }
        ]
      },
      {
        "id": "1bbbc0a8618364d6",
        "type": "tabs",
        "children": [
          {
            "id": "181667f3e07872a0",
            "type": "leaf",
            "state": {
              "type": "graph",
              "state": {}
            }
          }
        ]
      }
    ],
    "direction": "vertical"
  },
  "left": {
    "id": "3b65618d4ff1b557",
    "type": "split",
    "children": [
      {
        "id": "56c6222d5aa0b680",
        "type": "tabs",
        "children": [
          {
            "id": "eb87cf5b65d0e6c3",
            "type": "leaf",
            "state": {
              "type": "file-explorer",
              "state": {
                "sortOrder": "alphabetical"
              }
            }
          },
          {
            "id": "2e9eca35b15aaba0",
            "type": "leaf",
            "state": {
              "type": "search",
              "state": {
                "query": "",
                "matchingCase": false,
                "explainSearch": false,
                "collapseAll": false,
                "extraContext": false,
                "sortOrder": "alphabetical"
              }
            }
          },
          {
            "id": "03c1de160a337f1e",
            "type": "leaf",
            "state": {
              "type": "bookmarks",
              "state": {}
            }
          }
        ]
      }
    ],
    "direction": "horizontal",
    "width": 300
  },
  "right": {
    "id": "0dff6d987753e5aa",
    "type": "split",
    "children": [
      {
        "id": "ad609e85cc223a0d",
        "type": "tabs",
        "children": [
          {
            "id": "082238c11130b3f3",
            "type": "leaf",
            "state": {
              "type": "backlink",
              "state": {
                "file": "Welcome.md",
                "collapseAll": false,
                "extraContext": false,
                "sortOrder": "alphabetical",
                "showSearch": false,
                "searchQuery": "",
                "backlinkCollapsed": false,
                "unlinkedCollapsed": true
              }
            }
          },
          {
            "id": "a4f2243937002f2d",
            "type": "leaf",
            "state": {
              "type": "outgoing-link",
              "state": {
                "file": "Welcome.md",
                "linksCollapsed": false,
                "unlinkedCollapsed": true
              }
            }
          },
          {
            "id": "fcc529bbf1b41f4c",
            "type": "leaf",
            "state": {
              "type": "tag",
              "state": {
                "sortOrder": "frequency",
                "useHierarchy": true
              }
            }
          },
          {
            "id": "355d69796d65e14a",
            "type": "leaf",
            "state": {
              "type": "outline",
              "state": {
                "file": "Welcome.md"
              }
            }
          }
        ]
      }
    ],
    "direction": "horizontal",
    "width": 300,
    "collapsed": true
  },
  "left-ribbon": {
    "hiddenItems": {
      "switcher:Open quick switcher": false,
      "graph:Open graph view": false,
      "canvas:Create new canvas": false,
      "daily-notes:Open today's daily note": false,
      "templates:Insert template": false,
      "command-palette:Open command palette": false
    }
  },
  "active": "b9810ce725926b7d",
  "lastOpenFiles": [
    "Welcome.md"
  ]
}